cira/__init__.py
cira/alpaca_utils.py
cira/asset.py
cira/asset_option.py
cira/asset_stock.py
cira/assset_cryptocurrency.py
cira/auth.py
cira/config.py
cira/exchange.py
cira/log.py
cira/portfolio.py
cira/strategy.py
cira/util.py
cira-3.3.0.dist-info/LICENSE.txt
cira-3.3.0.dist-info/METADATA
cira-3.3.0.dist-info/WHEEL
cira-3.3.0.dist-info/top_level.txt
cira-3.3.0.dist-info/RECORD
