Metadata-Version: 2.1
Name: cira
Version: 3.3.0
Summary: A simpler library for the alapaca trade api
Home-page: https://github.com/AxelGard/cira
Author: Axel Gard
Author-email: axel.gard@tutanota.com
License: MIT
Classifier: Development Status :: 5 - Production/Stable
Classifier: Topic :: Office/Business :: Financial
Classifier: Programming Language :: Python :: 3.8
Classifier: License :: OSI Approved :: MIT License
License-File: LICENSE.txt
Requires-Dist: alpaca-py ==0.21.0
Requires-Dist: schedule ==1.2.0
Requires-Dist: matplotlib
Requires-Dist: pandas
Requires-Dist: numpy
